[
  {
    "name": "Elton",
    "avatar": "https://avatars.githubusercontent.com/u/70419?v=4",
    "content": "try comment",
    "createdAt": 1616566546364,
    "id": "yExH_XqN98ktmrj_gsRhdIRyl5kYNy"
  },
  {
    "name": "Elton",
    "avatar": "https://avatars.githubusercontent.com/u/70419?v=4",
    "content": "try comment",
    "createdAt": 1616566548125,
    "id": "gS8k1aybyVSKRcjdKUpFM9W58lDR_m"
  },
  {
    "name": "Elton",
    "avatar": "https://avatars.githubusercontent.com/u/70419?v=4",
    "content": "try comment",
    "createdAt": 1616566550512,
    "id": "axfbCRFKP5xAjHEz-Uhnu3nscRiTHn"
  },
  {
    "name": "Elton",
    "avatar": "https://avatars.githubusercontent.com/u/70419?v=4",
    "content": "try comment",
    "createdAt": 1616566553357,
    "id": "rHy0d5RoK6TSduggnqkIWUSXaKCYqS"
  },
  {
    "name": "Elton",
    "avatar": "https://avatars.githubusercontent.com/u/70419?v=4",
    "content": "try comment",
    "createdAt": 1616566556094,
    "id": "5LdvbpFNPmz8nznwOYs3uNYOg9JgfL"
  },
  {
    "name": "Elton",
    "avatar": "https://avatars.githubusercontent.com/u/70419?v=4",
    "content": "try comment",
    "createdAt": 1616566558898,
    "id": "Dxfb8H_pa7ECoYQ9q-HsCbCWWOWWlF"
  },
  {
    "name": "Elton",
    "avatar": "https://avatars.githubusercontent.com/u/70419?v=4",
    "content": "try comment",
    "createdAt": 1616566560661,
    "id": "DwIDn28s72yED0JaP6sCCoeK9-H2IA"
  },
  {
    "name": "Elton",
    "avatar": "https://avatars.githubusercontent.com/u/70419?v=4",
    "content": "try comment",
    "createdAt": 1616566562382,
    "id": "QAXFmUDYmZIDHIndc3nViWCaZ1sqBO"
  }
]